{"info": {"project": "apache/dubbo", "developers": 1, "edges": 1, "vertices": 2, "commits": 1, "id": 404, "agedays": 0, "refactorings": 1, "group": "Atomic", "language": "Java", "level": "Method"}, "commits_list": ["9cee44a6a"], "edges": [{"id": 489, "before": "dubbo-cluster.src.main.com.alibaba.dubbo.rpc.cluster.support.FailoverCluster#merge(Directory)", "lineB": null, "after": "dubbo-cluster.src.main.com.alibaba.dubbo.rpc.cluster.support.FailoverCluster#join(Directory)", "lineA": null, "ref": "RENAME", "sha1": "9cee44a6a"}]}