{"info": {"project": "apache/dubbo", "developers": 1, "edges": 1, "vertices": 2, "commits": 1, "id": 256, "agedays": 0.0, "refactorings": 1, "group": "Atomic", "language": "Java", "level": "Method"}, "commits_list": ["b04603124"], "edges": [{"entity_before_full_name": "dubbo-rpc.dubbo-rpc-default.src.main.com.alibaba.dubbo.rpc.protocol.dubbo.DubboCodec#decodeResponseData(Channel,ObjectInput,Object)", "entity_after_full_name": "dubbo-rpc.dubbo-rpc-default.src.main.com.alibaba.dubbo.rpc.protocol.dubbo.DecodeableRpcResult#decode(Channel,InputStream)", "refactoring_name": "MOVE_RENAME", "sha1": "b04603124"}]}