{"info": {"project": "facebook/react", "developers": 1, "edges": 1, "vertices": 2, "commits": 1, "id": 511, "agedays": 0, "refactorings": 1, "group": "Atomic", "language": "JavaScript", "level": "Function"}, "commits_list": ["c0e32a1b0"], "edges": [{"id": 622, "before": "src.renderers.dom.shared.ReactBrowserEventEmitter.js#injectReactEventListener", "lineB": 103, "after": "src.renderers.dom.shared.ReactBrowserEventEmitter.js#injectReactDOMEventListener", "lineA": 104, "ref": "RENAME", "sha1": "c0e32a1b0"}]}