{"info": {"project": "facebook/react", "developers": 1, "edges": 1, "vertices": 2, "commits": 1, "id": 401, "agedays": 0, "refactorings": 1, "group": "Atomic", "language": "JavaScript", "level": "Function", "summary": ""}, "commits_list": ["067cc24f5"], "edges": [{"id": 494, "before": "packages.react-reconciler.src.ReactProfilerTimer.js#stopBaseRenderTimerIfRunning", "lineB": 177, "after": "packages.react-reconciler.src.ReactProfilerTimer.js#stopProfilerTimerIfRunning", "lineA": 50, "ref": "RENAME", "sha1": "067cc24f5"}]}