{"info": {"project": "facebook/react", "developers": 1, "edges": 1, "vertices": 2, "commits": 1, "id": 533, "agedays": 0.0, "refactorings": 1, "group": "Atomic", "language": "JavaScript", "level": "Function"}, "commits_list": ["b27cb2ca2"], "edges": [{"entity_before_full_name": "src.renderers.shared.stack.reconciler.ReactUpdateQueue.js#validateCallback", "entity_after_full_name": "src.renderers.shared.utils.validateCallback.js#validateCallback", "refactoring_name": "MOVE", "sha1": "b27cb2ca2"}]}