{"info": {"project": "facebook/react", "developers": 1, "edges": 1, "vertices": 2, "commits": 1, "id": 215, "agedays": 0.0, "refactorings": 1, "group": "Atomic", "language": "JavaScript", "level": "Function"}, "commits_list": ["4d307de45"], "edges": [{"id": 263, "before": "packages.scheduler.src.forks.SchedulerHostConfig.mock.js#unstable_flushWithoutYielding", "lineB": 143, "after": "packages.scheduler.src.forks.SchedulerHostConfig.mock.js#unstable_flushAllWithoutAsserting", "lineA": 143, "ref": "RENAME", "sha1": "4d307de45"}]}