{"info": {"project": "facebook/react", "developers": 1, "edges": 1, "vertices": 2, "commits": 1, "id": 341, "agedays": 0.0, "refactorings": 1, "group": "Atomic", "language": "JavaScript", "level": "Function"}, "commits_list": ["3f4852fa5"], "edges": [{"entity_before_full_name": "packages.react-reconciler.src.ReactFiberCommitWork.js#commitWork", "entity_after_full_name": "packages.react-reconciler.src.ReactFiberCommitWork.js#commitSuspenseComponent", "refactoring_name": "EXTRACT", "sha1": "3f4852fa5"}]}