{"info": {"project": "facebook/react", "developers": 1, "edges": 1, "vertices": 2, "commits": 1, "id": 212, "agedays": 0, "refactorings": 1, "group": "Atomic", "language": "JavaScript", "level": "Function", "summary": ""}, "commits_list": ["4d307de45"], "edges": [{"id": 260, "before": "packages.scheduler.src.forks.SchedulerHostConfig.mock.js#yieldValue", "lineB": 194, "after": "packages.scheduler.src.forks.SchedulerHostConfig.mock.js#unstable_yieldValue", "lineA": 194, "ref": "RENAME", "sha1": "4d307de45"}]}