{"info": {"project": "facebook/react", "developers": 1, "edges": 1, "vertices": 2, "commits": 1, "id": 379, "agedays": 0.0, "refactorings": 1, "group": "Atomic", "language": "JavaScript", "level": "Function"}, "commits_list": ["769b1f270"], "edges": [{"id": 466, "before": "packages.react-reconciler.src.ReactFiberBeginWork.js#updateSimplePureComponent", "lineB": 302, "after": "packages.react-reconciler.src.ReactFiberBeginWork.js#updateSimpleMemoComponent", "lineA": 302, "ref": "RENAME", "sha1": "769b1f270"}]}