{"info": {"project": "facebook/react", "developers": 1, "edges": 1, "vertices": 2, "commits": 1, "id": 152, "agedays": 0, "refactorings": 1, "group": "Atomic", "language": "JavaScript", "level": "Function", "summary": ""}, "commits_list": ["3af05de1a"], "edges": [{"id": 178, "before": "packages.react-ui.events.src.dom.Press.js#calculateResponderRegion", "lineB": 322, "after": "packages.react-ui.events.src.dom.PressLegacy.js#calculateResponderRegion", "lineA": 322, "ref": "MOVE", "sha1": "3af05de1a"}]}