{"info": {"project": "facebook/react", "developers": 1, "edges": 1, "vertices": 2, "commits": 1, "id": 601, "agedays": 0, "refactorings": 1, "group": "Atomic", "language": "JavaScript", "level": "Function"}, "commits_list": ["df033180f"], "edges": [{"id": 733, "before": "src.addons.transitions.ReactTransitionGroup.js#componentDidUpdate", "lineB": 104, "after": "src.addons.transitions.ReactTransitionGroup.js.ReactTransitionGroup#componentDidUpdate", "lineA": 100, "ref": "INTERNAL_MOVE", "sha1": "df033180f"}]}