{"info": {"project": "square/okhttp", "developers": 1, "edges": 1, "vertices": 2, "commits": 1, "id": 159, "agedays": 0, "refactorings": 1, "group": "Atomic", "language": "Java", "level": "Method", "summary": ""}, "commits_list": ["3e161686a"], "edges": [{"id": 241, "before": "okhttp.src.main.okhttp3.internal.http.HttpEngine#recover(IOException,boolean,Request)", "lineB": null, "after": "okhttp.src.main.okhttp3.internal.http.RetryAndFollowUpInterceptor#recover(IOException,boolean,Request)", "lineA": null, "ref": "MOVE", "sha1": "3e161686a"}]}