{"info": {"project": "hexojs/hexo", "developers": 1, "edges": 4, "vertices": 4, "commits": 2, "id": 120, "agedays": 44.93061342592593, "refactorings": 2, "group": "Overtime", "language": "JavaScript", "level": "Function"}, "commits_list": ["fa085a20", "75f9362a"], "edges": [{"id": 166, "before": "lib.box.index.js#escapeBackslash", "lineB": 74, "after": "lib.box.index.js#_handleDeletedFile", "lineA": 253, "ref": "INLINE", "sha1": "fa085a20"}, {"id": 154, "before": "lib.box.index.js#escapeBackslashWindows", "lineB": 76, "after": "lib.box.index.js#escapeBackslash", "lineA": 70, "ref": "RENAME", "sha1": "75f9362a"}, {"id": 167, "before": "lib.box.index.js#escapeBackslash", "lineB": 78, "after": "lib.box.index.js#escapeBackslashWindows", "lineA": 80, "ref": "RENAME", "sha1": "fa085a20"}, {"id": 165, "before": "lib.box.index.js#escapeBackslash", "lineB": 74, "after": "lib.box.index.js#_handleUpdatedFile", "lineA": 204, "ref": "INLINE", "sha1": "fa085a20"}]}