{"info": {"project": "parcel-bundler/parcel", "developers": 1, "edges": 2, "vertices": 3, "commits": 2, "id": 94, "agedays": 27.47978009259259, "refactorings": 2, "group": "Overtime", "language": "JavaScript", "level": "Function"}, "commits_list": ["a89853ee", "6fcca9cf"], "edges": [{"entity_before_full_name": "packages.core.parcel-bundler.src.Bundle.js.Bundle#getChildBundle", "entity_after_full_name": "packages.core.parcel-bundler.src.Bundle.js.Bundle#getSiblingBundle", "refactoring_name": "RENAME", "sha1": "a89853ee"}, {"entity_before_full_name": "packages.core.parcel-bundler.src.Bundle.js.Bundle#getChildBundle", "entity_after_full_name": "packages.core.parcel-bundler.src.Bundle.js.Bundle#createChildBundle", "refactoring_name": "EXTRACT", "sha1": "6fcca9cf"}]}