{"info": {"project": "parcel-bundler/parcel", "developers": 1, "edges": 3, "vertices": 4, "commits": 3, "id": 69, "agedays": 270.57560185185184, "refactorings": 3, "group": "Overtime", "language": "JavaScript", "level": "Function"}, "commits_list": ["38d4a830", "dd3ea464", "e4cee192"], "edges": [{"entity_before_full_name": "packages.core.parcel-bundler.src.Bundle.js.Bundle#resolveModule", "entity_after_full_name": "packages.core.parcel-bundler.src.Bundle.js.Bundle#resolveAsset", "refactoring_name": "RENAME", "sha1": "38d4a830"}, {"entity_before_full_name": "packages.core.parcel-bundler.src.Bundler.js.Bundler#resolveAsset", "entity_after_full_name": "packages.core.parcel-bundler.src.Bundler.js.Bundler#getLoadedAsset", "refactoring_name": "EXTRACT", "sha1": "dd3ea464"}, {"entity_before_full_name": "packages.core.parcel-bundler.src.Bundle.js.Bundle#resolveAsset", "entity_after_full_name": "packages.core.parcel-bundler.src.Bundler.js.Bundler#resolveAsset", "refactoring_name": "MOVE", "sha1": "e4cee192"}]}