{"info": {"project": "elastic/elasticsearch", "developers": 1, "edges": 1, "vertices": 2, "commits": 1, "id": 1886, "agedays": 0.0, "refactorings": 1, "group": "Atomic", "language": "Java", "level": "Method"}, "commits_list": ["e9cd0556c16"], "edges": [{"entity_before_full_name": "x-pack.plugin.core.src.main.org.elasticsearch.license.License.Status#readFrom(StreamInput)", "entity_after_full_name": "x-pack.protocol.src.main.org.elasticsearch.protocol.license.LicenseStatus#fromString(String)", "refactoring_name": "EXTRACT", "sha1": "e9cd0556c16"}]}