{"info": {"project": "elastic/elasticsearch", "developers": 1, "edges": 1, "vertices": 2, "commits": 1, "id": 289, "agedays": 0, "refactorings": 1, "group": "Atomic", "language": "Java", "level": "Method", "summary": ""}, "commits_list": ["7b866e00616"], "edges": [{"id": 325, "before": "x-pack.plugin.ml.src.main.org.elasticsearch.xpack.ml.action.TransportGetDatafeedsStatsAction#newResponse()", "lineB": null, "after": "x-pack.plugin.ml.src.main.org.elasticsearch.xpack.ml.action.TransportGetDatafeedsStatsAction#read(StreamInput)", "lineA": null, "ref": "RENAME", "sha1": "7b866e00616"}]}