{"info": {"project": "elastic/elasticsearch", "developers": 1, "edges": 1, "vertices": 2, "commits": 1, "id": 1469, "agedays": 0.0, "refactorings": 1, "group": "Atomic", "language": "Java", "level": "Method"}, "commits_list": ["84ef91529cf"], "edges": [{"id": 2025, "before": "x-pack.plugin.core.src.main.org.elasticsearch.xpack.core.security.authz.permission.ApplicationPermission.PermissionEntry#grants(ApplicationPrivilege,Automaton)", "lineB": null, "after": "x-pack.plugin.core.src.main.org.elasticsearch.xpack.core.security.authz.permission.ApplicationPermission.PermissionEntry#matchesPrivilege(ApplicationPrivilege)", "lineA": null, "ref": "EXTRACT", "sha1": "84ef91529cf"}]}