{"info": {"project": "elastic/elasticsearch", "developers": 1, "edges": 1, "vertices": 2, "commits": 1, "id": 1796, "agedays": 0, "refactorings": 1, "group": "Atomic", "language": "Java", "level": "Method", "summary": ""}, "commits_list": ["5f696e15eac"], "edges": [{"id": 2428, "before": "modules.ingest-common.src.main.org.elasticsearch.ingest.common.LowercaseProcessor#process(String)", "lineB": null, "after": "modules.ingest-common.src.main.org.elasticsearch.ingest.common.LowercaseProcessor#apply(String)", "lineA": null, "ref": "EXTRACT", "sha1": "5f696e15eac"}]}