{"info": {"project": "elastic/elasticsearch", "developers": 1, "edges": 1, "vertices": 2, "commits": 1, "id": 1285, "agedays": 0.0, "refactorings": 1, "group": "Atomic", "language": "Java", "level": "Method"}, "commits_list": ["f0a3d326022"], "edges": [{"entity_before_full_name": "x-pack.plugin.sql.jdbc.src.main.org.elasticsearch.xpack.sql.jdbc.jdbc.JdbcPreparedStatement#setObject(int,Object,int,int)", "entity_after_full_name": "x-pack.plugin.sql.jdbc.src.main.org.elasticsearch.xpack.sql.jdbc.jdbc.JdbcPreparedStatement#setObject(int,Object,SQLType,int)", "refactoring_name": "EXTRACT", "sha1": "f0a3d326022"}]}