{"info": {"project": "elastic/elasticsearch", "developers": 1, "edges": 1, "vertices": 2, "commits": 1, "id": 98, "agedays": 0, "refactorings": 1, "group": "Atomic", "language": "Java", "level": "Method"}, "commits_list": ["8cdce05c6b0"], "edges": [{"id": 111, "before": "x-pack.plugin.data-frame.src.main.org.elasticsearch.xpack.dataframe.transforms.DataFrameTransformTask#start(Long,boolean,ActionListener)", "lineB": null, "after": "x-pack.plugin.data-frame.src.main.org.elasticsearch.xpack.dataframe.transforms.DataFrameTransformTask#start(Long,boolean,boolean,ActionListener)", "lineA": null, "ref": "EXTRACT", "sha1": "8cdce05c6b0"}]}