{"info": {"project": "elastic/elasticsearch", "developers": 1, "edges": 1, "vertices": 2, "commits": 1, "id": 1558, "agedays": 0, "refactorings": 1, "group": "Atomic", "language": "Java", "level": "Method", "summary": ""}, "commits_list": ["81e9150c7a6"], "edges": [{"id": 2149, "before": "server.src.main.org.elasticsearch.env.NodeEnvironment#resolveCustomLocation(IndexSettings,ShardId)", "lineB": null, "after": "server.src.main.org.elasticsearch.env.NodeEnvironment#resolveCustomLocation(IndexSettings,ShardId,Path,int)", "lineA": null, "ref": "EXTRACT", "sha1": "81e9150c7a6"}]}