{"info": {"project": "elastic/elasticsearch", "developers": 1, "edges": 1, "vertices": 2, "commits": 1, "id": 1346, "agedays": 0, "refactorings": 1, "group": "Atomic", "language": "Java", "level": "Method", "summary": ""}, "commits_list": ["574ec6686ed"], "edges": [{"id": 1831, "before": "x-pack.plugin.security.src.main.org.elasticsearch.xpack.security.authc.Realms#initRealms()", "lineB": null, "after": "x-pack.plugin.core.src.main.org.elasticsearch.xpack.core.security.authc.RealmConfig.RealmIdentifier#getName()", "lineA": null, "ref": "EXTRACT_MOVE", "sha1": "574ec6686ed"}]}