{"info": {"project": "elastic/elasticsearch", "developers": 1, "edges": 1, "vertices": 2, "commits": 1, "id": 998, "agedays": 0.0, "refactorings": 1, "group": "Atomic", "language": "Java", "level": "Method"}, "commits_list": ["2439f687455"], "edges": [{"id": 1298, "before": "server.src.main.org.elasticsearch.cluster.routing.RoutingService#performReroute(String)", "lineB": null, "after": "server.src.main.org.elasticsearch.cluster.routing.RoutingService#reroute(String)", "lineA": null, "ref": "INLINE", "sha1": "2439f687455"}]}