{"info": {"project": "elastic/elasticsearch", "developers": 1, "edges": 1, "vertices": 2, "commits": 1, "id": 645, "agedays": 0.0, "refactorings": 1, "group": "Atomic", "language": "Java", "level": "Method"}, "commits_list": ["ee51702e780"], "edges": [{"entity_before_full_name": "client.rest.src.main.org.elasticsearch.client.RestClient#hostsToNodes(HttpHost[])", "entity_after_full_name": "client.rest.src.main.org.elasticsearch.client.RestClient#builder(HttpHost[])", "refactoring_name": "INLINE", "sha1": "ee51702e780"}]}