{"info": {"project": "elastic/elasticsearch", "developers": 1, "edges": 1, "vertices": 2, "commits": 1, "id": 1916, "agedays": 0, "refactorings": 1, "group": "Atomic", "language": "Java", "level": "Method", "summary": ""}, "commits_list": ["eee1a451fc3"], "edges": [{"id": 2571, "before": "server.src.main.org.elasticsearch.transport.TcpChannel#closeChannel(C,boolean)", "lineB": null, "after": "server.src.main.org.elasticsearch.common.network.CloseableChannel#closeChannel(C,boolean)", "lineA": null, "ref": "PULL_UP", "sha1": "eee1a451fc3"}]}