{"info": {"project": "elastic/elasticsearch", "developers": 1, "edges": 1, "vertices": 2, "commits": 1, "id": 1327, "agedays": 0, "refactorings": 1, "group": "Atomic", "language": "Java", "level": "Method"}, "commits_list": ["85a8b517bd6"], "edges": [{"id": 1808, "before": "client.rest-high-level.src.main.org.elasticsearch.client.security.user.User#username()", "lineB": null, "after": "client.rest-high-level.src.main.org.elasticsearch.client.security.user.User#getUsername()", "lineA": null, "ref": "RENAME", "sha1": "85a8b517bd6"}]}