{"info": {"project": "elastic/elasticsearch", "developers": 1, "edges": 1, "vertices": 2, "commits": 1, "id": 1859, "agedays": 0, "refactorings": 1, "group": "Atomic", "language": "Java", "level": "Method", "summary": ""}, "commits_list": ["4192f387b41"], "edges": [{"id": 2499, "before": "x-pack.plugin.sql.src.main.org.elasticsearch.xpack.sql.parser.ExpressionBuilder#visitExtract(ExtractContext)", "lineB": null, "after": "x-pack.plugin.sql.src.main.org.elasticsearch.xpack.sql.parser.ExpressionBuilder#visitExtractExpression(ExtractExpressionContext)", "lineA": null, "ref": "RENAME", "sha1": "4192f387b41"}]}