{"info": {"project": "elastic/elasticsearch", "developers": 1, "edges": 2, "vertices": 3, "commits": 2, "id": 646, "agedays": 7.009791666666667, "refactorings": 1, "group": "Overtime", "language": "Java", "level": "Method"}, "commits_list": ["0ca375ed42f", "cb2bd0bb6b9"], "edges": [{"entity_before_full_name": "x-pack.plugin.security.src.main.org.elasticsearch.xpack.security.transport.nio.SSLDriver#ensureNetBufferSize(ByteBuffer)", "entity_after_full_name": "x-pack.plugin.security.src.main.org.elasticsearch.xpack.security.transport.nio.SSLDriver#ensureNetworkReadBufferSize()", "refactoring_name": "INLINE", "sha1": "0ca375ed42f"}, {"entity_before_full_name": "x-pack.plugin.security.src.main.org.elasticsearch.xpack.security.transport.nio.SSLDriver#ensureNetworkReadBufferSize()", "entity_after_full_name": "x-pack.plugin.security.src.main.org.elasticsearch.xpack.security.transport.nio.SSLDriver#unwrap(InboundChannelBuffer,InboundChannelBuffer)", "refactoring_name": "INLINE", "sha1": "cb2bd0bb6b9"}]}