{"info": {"project": "elastic/elasticsearch", "developers": 1, "edges": 1, "vertices": 2, "commits": 1, "id": 625, "agedays": 0.0, "refactorings": 1, "group": "Atomic", "language": "Java", "level": "Method"}, "commits_list": ["307bc17f051"], "edges": [{"entity_before_full_name": "x-pack.plugin.security.src.main.org.elasticsearch.xpack.security.authc.TokenService#prependVersionAndEncode(Version,String)", "entity_after_full_name": "x-pack.plugin.security.src.main.org.elasticsearch.xpack.security.authc.TokenService#prependVersionAndEncodeRefreshToken(Version,String)", "refactoring_name": "RENAME", "sha1": "307bc17f051"}]}