{"info": {"project": "elastic/elasticsearch", "developers": 1, "edges": 3, "vertices": 2, "commits": 3, "id": 1114, "agedays": 0, "refactorings": 1, "group": "Overtime", "language": "Java", "level": "Method", "summary": ""}, "commits_list": ["ec0dc2c0e90", "5bc7822562a", "96d279ed83e"], "edges": [{"id": 1448, "before": "server.src.main.org.elasticsearch.index.mapper.GeoShapeFieldMapper.GeoShapeFieldType#setPointsOnly(boolean)", "lineB": null, "after": "server.src.main.org.elasticsearch.index.mapper.LegacyGeoShapeFieldMapper.GeoShapeFieldType#setPointsOnly(boolean)", "lineA": null, "ref": "MOVE", "sha1": "ec0dc2c0e90"}, {"id": 1525, "before": "server.src.main.org.elasticsearch.index.mapper.GeoShapeFieldMapper.GeoShapeFieldType#setPointsOnly(boolean)", "lineB": null, "after": "server.src.main.org.elasticsearch.index.mapper.LegacyGeoShapeFieldMapper.GeoShapeFieldType#setPointsOnly(boolean)", "lineA": null, "ref": "MOVE", "sha1": "5bc7822562a"}, {"id": 1466, "before": "server.src.main.org.elasticsearch.index.mapper.LegacyGeoShapeFieldMapper.GeoShapeFieldType#setPointsOnly(boolean)", "lineB": null, "after": "server.src.main.org.elasticsearch.index.mapper.GeoShapeFieldMapper.GeoShapeFieldType#setPointsOnly(boolean)", "lineA": null, "ref": "MOVE", "sha1": "96d279ed83e"}]}