{"info": {"project": "elastic/elasticsearch", "developers": 1, "edges": 1, "vertices": 2, "commits": 1, "id": 168, "agedays": 0, "refactorings": 1, "group": "Atomic", "language": "Java", "level": "Method", "summary": ""}, "commits_list": ["570e406e917"], "edges": [{"id": 190, "before": "server.src.main.org.elasticsearch.rest.MethodHandlers#addMethod(RestRequest.Method,RestHandler)", "lineB": null, "after": "server.src.main.org.elasticsearch.rest.MethodHandlers#addMethods(RestHandler,RestRequest.Method[])", "lineA": null, "ref": "INLINE", "sha1": "570e406e917"}]}