{"info": {"project": "elastic/elasticsearch", "developers": 1, "edges": 1, "vertices": 2, "commits": 1, "id": 184, "agedays": 0.0, "refactorings": 1, "group": "Atomic", "language": "Java", "level": "Method"}, "commits_list": ["724a0e40a36"], "edges": [{"entity_before_full_name": "x-pack.plugin.core.src.main.org.elasticsearch.xpack.core.ssl.TrustConfig#getStore(Environment,String,String,SecureString)", "entity_after_full_name": "x-pack.plugin.core.src.main.org.elasticsearch.xpack.core.ssl.TrustConfig#getStore(Path,String,SecureString)", "refactoring_name": "EXTRACT", "sha1": "724a0e40a36"}]}