{"info": {"project": "ReactiveX/RxJava", "developers": 1, "edges": 2, "vertices": 3, "commits": 2, "id": 1042, "agedays": 0, "refactorings": 2, "group": "Overtime", "language": "Java", "level": "Method", "summary": ""}, "commits_list": ["10d8ca9e1", "96eebf284"], "edges": [{"id": 1337, "before": "r-core.src.main.rx.Observable#createSubscription(Object)", "lineB": null, "after": "r-core.src.main.rx.subscriptions.Subscriptions#createSubscription(Object)", "lineA": null, "ref": "MOVE", "sha1": "10d8ca9e1"}, {"id": 1334, "before": "r-core.src.main.rx.subscriptions.Subscriptions#createSubscription(Object)", "lineB": null, "after": "r-core.src.main.rx.subscriptions.Subscriptions#create(Object)", "lineA": null, "ref": "RENAME", "sha1": "96eebf284"}]}