{"info": {"project": "ReactiveX/RxJava", "developers": 1, "edges": 2, "vertices": 3, "commits": 1, "id": 145, "agedays": 0, "refactorings": 1, "group": "Atomic", "language": "Java", "level": "Method"}, "commits_list": ["d85d40ecb"], "edges": [{"id": 259, "before": "src.main.io.reactivex.subscribers.TestSubscriber#assertValueSet(Collection)", "lineB": null, "after": "src.main.io.reactivex.observers.BaseTestConsumer#assertValueSet(Collection)", "lineA": null, "ref": "PULL_UP", "sha1": "d85d40ecb"}, {"id": 275, "before": "src.main.io.reactivex.observers.TestObserver#assertValueSet(Collection)", "lineB": null, "after": "src.main.io.reactivex.observers.BaseTestConsumer#assertValueSet(Collection)", "lineA": null, "ref": "PULL_UP", "sha1": "d85d40ecb"}]}