{"info": {"project": "ReactiveX/RxJava", "developers": 1, "edges": 2, "vertices": 3, "commits": 2, "id": 225, "agedays": 153.71141203703704, "refactorings": 2, "group": "Overtime", "language": "Java", "level": "Method"}, "commits_list": ["10325b90e", "35c8da6ca"], "edges": [{"entity_before_full_name": "src.main.io.reactivex.Observable#amb(Publisher[])", "entity_after_full_name": "src.main.io.reactivex.Flowable#amb(Publisher[])", "refactoring_name": "MOVE", "sha1": "10325b90e"}, {"entity_before_full_name": "src.main.io.reactivex.Flowable#amb(Publisher[])", "entity_after_full_name": "src.main.io.reactivex.Flowable#ambArray(Publisher[])", "refactoring_name": "RENAME", "sha1": "35c8da6ca"}]}