{"info": {"project": "ReactiveX/RxJava", "developers": 1, "edges": 2, "vertices": 3, "commits": 2, "id": 232, "agedays": 153, "refactorings": 2, "group": "Overtime", "language": "Java", "level": "Method", "summary": ""}, "commits_list": ["9fb404033", "10325b90e"], "edges": [{"id": 367, "before": "src.main.io.reactivex.Flowable#mergeDelayError(int,int,Publisher[])", "lineB": null, "after": "src.main.io.reactivex.Flowable#mergeArrayDelayError(int,int,Publisher[])", "lineA": null, "ref": "RENAME", "sha1": "9fb404033"}, {"id": 937, "before": "src.main.io.reactivex.Observable#mergeDelayError(int,int,Publisher[])", "lineB": null, "after": "src.main.io.reactivex.Flowable#mergeDelayError(int,int,Publisher[])", "lineA": null, "ref": "MOVE", "sha1": "10325b90e"}]}