{"info": {"project": "ReactiveX/RxJava", "developers": 1, "edges": 1, "vertices": 2, "commits": 1, "id": 177, "agedays": 0, "refactorings": 1, "group": "Atomic", "language": "Java", "level": "Method", "summary": ""}, "commits_list": ["1145819b6"], "edges": [{"id": 307, "before": "src.main.io.reactivex.internal.queue.BaseArrayQueue#soElement(int,E)", "lineB": null, "after": "src.main.io.reactivex.internal.queue.SpscArrayQueue#soElement(int,E)", "lineA": null, "ref": "MOVE", "sha1": "1145819b6"}]}