{"info": {"project": "spring-projects/spring-framework", "developers": 1, "edges": 1, "vertices": 2, "commits": 1, "id": 85, "agedays": 0.0, "refactorings": 1, "group": "Atomic", "language": "Java", "level": "Method"}, "commits_list": ["a5cb8799fa"], "edges": [{"id": 139, "before": "spring-context.src.main.org.springframework.validation.beanvalidation.SpringValidatorAdapter#requiresMessageFormat(ConstraintViolation)", "lineB": null, "after": "spring-context.src.main.org.springframework.validation.beanvalidation.SpringValidatorAdapter#containsSpringStylePlaceholder(String)", "lineA": null, "ref": "EXTRACT", "sha1": "a5cb8799fa"}]}