{"info": {"project": "spring-projects/spring-framework", "developers": 1, "edges": 1, "vertices": 2, "commits": 1, "id": 1684, "agedays": 0, "refactorings": 1, "group": "Atomic", "language": "Java", "level": "Method"}, "commits_list": ["5d8fac86d7"], "edges": [{"id": 2456, "before": "spring-orm.src.main.org.springframework.orm.hibernate3.support.OpenSessionInViewInterceptor.SessionBindingCallableInterceptor#preProcess(NativeWebRequest,Callable)", "lineB": null, "after": "spring-orm.src.main.org.springframework.orm.hibernate3.support.AsyncRequestInterceptor#preProcess(NativeWebRequest,Callable)", "lineA": null, "ref": "MOVE", "sha1": "5d8fac86d7"}]}