{"info": {"project": "spring-projects/spring-framework", "developers": 2, "edges": 2, "vertices": 3, "commits": 2, "id": 1157, "agedays": 245, "refactorings": 1, "group": "Overtime", "language": "Java", "level": "Method"}, "commits_list": ["bddc4373fb", "44651fdf7c"], "edges": [{"id": 1920, "before": "spring-core.src.main.org.springframework.core.convert.support.ObjectToObjectConverter#getOfMethod(Class,Class)", "lineB": null, "after": "spring-core.src.main.org.springframework.core.convert.support.ObjectToObjectConverter#getFactoryMethod(Class,Class)", "lineA": null, "ref": "RENAME", "sha1": "bddc4373fb"}, {"id": 1681, "before": "spring-core.src.main.org.springframework.core.convert.support.ObjectToObjectConverter#getFactoryMethod(Class,Class)", "lineB": null, "after": "spring-core.src.main.org.springframework.core.convert.support.ObjectToObjectConverter#determineFactoryMethod(Class,Class)", "lineA": null, "ref": "RENAME", "sha1": "44651fdf7c"}]}