{"info": {"project": "spring-projects/spring-framework", "developers": 1, "edges": 1, "vertices": 2, "commits": 1, "id": 919, "agedays": 0, "refactorings": 1, "group": "Atomic", "language": "Java", "level": "Method"}, "commits_list": ["a7ec6dc0af"], "edges": [{"id": 1329, "before": "spring-context.src.main.org.springframework.context.annotation.ConfigurationClassParser.ImportStack#removeImportingClassFor(String)", "lineB": null, "after": "spring-context.src.main.org.springframework.context.annotation.ConfigurationClassParser.ImportStack#removeImportingClass(String)", "lineA": null, "ref": "RENAME", "sha1": "a7ec6dc0af"}]}