{"info": {"project": "spring-projects/spring-framework", "developers": 1, "edges": 1, "vertices": 2, "commits": 1, "id": 2433, "agedays": 0, "refactorings": 1, "group": "Atomic", "language": "Java", "level": "Method"}, "commits_list": ["9b0c66dc6c"], "edges": [{"id": 3512, "before": "org.springframework.web.servlet.src.main.org.springframework.web.servlet.mvc.method.annotation.RequestMappingHandlerMapping.RequestMappingInfoComparator#compare(RequestMappingInfo,RequestMappingInfo)", "lineB": null, "after": "org.springframework.web.servlet.src.main.org.springframework.web.servlet.mvc.method.condition.RequestMethodsRequestCondition#compareTo(RequestMethodsRequestCondition)", "lineA": null, "ref": "EXTRACT_MOVE", "sha1": "9b0c66dc6c"}]}