{"info": {"project": "spring-projects/spring-framework", "developers": 1, "edges": 4, "vertices": 5, "commits": 1, "id": 367, "agedays": 0, "refactorings": 2, "group": "Atomic", "language": "Java", "level": "Method"}, "commits_list": ["a1d209726c"], "edges": [{"id": 514, "before": "spring-core.src.main.org.springframework.asm.ClassReader#readCode(MethodVisitor,Context,int)", "lineB": null, "after": "spring-core.src.main.org.springframework.asm.ClassReader#getTypeAnnotationBytecodeOffset(int[],int)", "lineA": null, "ref": "EXTRACT", "sha1": "a1d209726c"}, {"id": 518, "before": "spring-core.src.main.org.springframework.asm.ClassReader#readCode(MethodVisitor,Context,int)", "lineB": null, "after": "spring-core.src.main.org.springframework.asm.Label#accept(MethodVisitor,boolean)", "lineA": null, "ref": "EXTRACT_MOVE", "sha1": "a1d209726c"}, {"id": 519, "before": "spring-core.src.main.org.springframework.asm.ClassReader#readCode(MethodVisitor,Context,int)", "lineB": null, "after": "spring-core.src.main.org.springframework.asm.ClassReader#createLabel(int,Label[])", "lineA": null, "ref": "EXTRACT", "sha1": "a1d209726c"}, {"id": 513, "before": "spring-core.src.main.org.springframework.asm.ClassReader#readCode(MethodVisitor,Context,int)", "lineB": null, "after": "spring-core.src.main.org.springframework.asm.ClassReader#createDebugLabel(int,Label[])", "lineA": null, "ref": "EXTRACT", "sha1": "a1d209726c"}]}