{"info": {"project": "spring-projects/spring-framework", "developers": 1, "edges": 2, "vertices": 3, "commits": 1, "id": 1183, "agedays": 0.0, "refactorings": 1, "group": "Atomic", "language": "Java", "level": "Method"}, "commits_list": ["aedef43a9a"], "edges": [{"id": 1732, "before": "spring-core.src.main.org.springframework.core.annotation.DefaultAnnotationAttributeExtractor#getAnnotation()", "lineB": null, "after": "spring-core.src.main.org.springframework.core.annotation.DefaultAnnotationAttributeExtractor#getRawAttributeValue(Method)", "lineA": null, "ref": "INLINE", "sha1": "aedef43a9a"}, {"id": 1729, "before": "spring-core.src.main.org.springframework.core.annotation.DefaultAnnotationAttributeExtractor#getAnnotation()", "lineB": null, "after": "spring-core.src.main.org.springframework.core.annotation.DefaultAnnotationAttributeExtractor#getRawAttributeValue(String)", "lineA": null, "ref": "INLINE", "sha1": "aedef43a9a"}]}