{"info": {"project": "spring-projects/spring-framework", "developers": 1, "edges": 1, "vertices": 2, "commits": 1, "id": 2642, "agedays": 0, "refactorings": 1, "group": "Atomic", "language": "Java", "level": "Method"}, "commits_list": ["2ce5090d00"], "edges": [{"id": 3865, "before": "org.springframework.core.src.main.org.springframework.core.annotation.AnnotationUtils#searchForAnnotationOnInterfaces(Method,Class,Class[])", "lineB": null, "after": "org.springframework.core.src.main.org.springframework.core.annotation.AnnotationUtils#searchOnInterfaces(Method,Class,Class[])", "lineA": null, "ref": "RENAME", "sha1": "2ce5090d00"}]}