{"info": {"project": "spring-projects/spring-framework", "developers": 1, "edges": 1, "vertices": 2, "commits": 1, "id": 3101, "agedays": 0, "refactorings": 1, "group": "Atomic", "language": "Java", "level": "Method", "summary": ""}, "commits_list": ["0b4e7cc5ed"], "edges": [{"id": 4505, "before": "org.springframework.jms.src.main.org.springframework.jms.core.JmsTemplate#doReceive(Session,MessageConsumer)", "lineB": null, "after": "org.springframework.jms.src.main.org.springframework.jms.core.JmsTemplate#doReceive(MessageConsumer,long)", "lineA": null, "ref": "EXTRACT", "sha1": "0b4e7cc5ed"}]}