{"info": {"project": "spring-projects/spring-framework", "developers": 1, "edges": 1, "vertices": 2, "commits": 1, "id": 1080, "agedays": 0, "refactorings": 1, "group": "Atomic", "language": "Java", "level": "Method"}, "commits_list": ["5ac31fb39d"], "edges": [{"id": 1566, "before": "spring-web.src.main.org.springframework.http.converter.ResourceHttpMessageConverter#print(OutputStream,String)", "lineB": null, "after": "spring-web.src.main.org.springframework.http.converter.ResourceRegionHttpMessageConverter#print(OutputStream,String)", "lineA": null, "ref": "MOVE", "sha1": "5ac31fb39d"}]}