{"info": {"project": "spring-projects/spring-framework", "developers": 1, "edges": 1, "vertices": 2, "commits": 1, "id": 2975, "agedays": 0, "refactorings": 1, "group": "Atomic", "language": "Java", "level": "Method"}, "commits_list": ["ec6cea54bc"], "edges": [{"id": 4332, "before": "org.springframework.context.src.main.org.springframework.scheduling.annotation.AsyncAnnotationBeanPostProcessor#setBeanFactory(BeanFactory)", "lineB": null, "after": "org.springframework.context.src.main.org.springframework.scheduling.annotation.AsyncAnnotationBeanPostProcessor#afterPropertiesSet()", "lineA": null, "ref": "RENAME", "sha1": "ec6cea54bc"}]}