{"info": {"project": "spring-projects/spring-framework", "developers": 1, "edges": 1, "vertices": 2, "commits": 1, "id": 2064, "agedays": 0, "refactorings": 1, "group": "Atomic", "language": "Java", "level": "Method"}, "commits_list": ["2ab2c2e9ce"], "edges": [{"id": 3002, "before": "spring-expression.src.main.org.springframework.expression.spel.ast.CompoundExpression#getValueInternal(ExpressionState)", "lineB": null, "after": "spring-expression.src.main.org.springframework.expression.spel.ast.CompoundExpression#getValueRef(ExpressionState)", "lineA": null, "ref": "EXTRACT", "sha1": "2ab2c2e9ce"}]}