{"info": {"project": "spring-projects/spring-framework", "developers": 1, "edges": 1, "vertices": 2, "commits": 1, "id": 169, "agedays": 0, "refactorings": 1, "group": "Atomic", "language": "Java", "level": "Method", "summary": ""}, "commits_list": ["f065abac93"], "edges": [{"id": 235, "before": "spring-core.src.main.org.springframework.core.annotation.OrderUtils#getOrder(Class)", "lineB": null, "after": "spring-core.src.main.org.springframework.core.annotation.OrderUtils#getOrderFromAnnotations(AnnotatedElement,MergedAnnotations)", "lineA": null, "ref": "EXTRACT", "sha1": "f065abac93"}]}