{"info": {"project": "spring-projects/spring-framework", "developers": 1, "edges": 1, "vertices": 2, "commits": 1, "id": 559, "agedays": 0.0, "refactorings": 1, "group": "Atomic", "language": "Java", "level": "Method"}, "commits_list": ["b0fc83ee05"], "edges": [{"entity_before_full_name": "spring-webmvc.src.main.org.springframework.web.servlet.resource.CssLinkResourceTransformer.AbstractLinkParser#addLink(int,String,String,Set)", "entity_after_full_name": "spring-webmvc.src.main.org.springframework.web.servlet.resource.CssLinkResourceTransformer.AbstractLinkParser#extractLink(int,String,String,SortedSet)", "refactoring_name": "RENAME", "sha1": "b0fc83ee05"}]}