{"info": {"project": "spring-projects/spring-framework", "developers": 1, "edges": 1, "vertices": 2, "commits": 1, "id": 1841, "agedays": 0.0, "refactorings": 1, "group": "Atomic", "language": "Java", "level": "Method"}, "commits_list": ["dad7115c23"], "edges": [{"entity_before_full_name": "spring-websocket.src.main.org.springframework.web.socket.sockjs.SockJsFrame#isSockJsEscapeCharacter(char)", "entity_after_full_name": "spring-websocket.src.main.org.springframework.web.socket.sockjs.support.AbstractSockJsMessageCodec#isSockJsSpecialChar(char)", "refactoring_name": "MOVE_RENAME", "sha1": "dad7115c23"}]}