{"info": {"project": "select2/select2", "developers": 2, "edges": 2, "vertices": 3, "commits": 2, "id": 46, "agedays": 349, "refactorings": 2, "group": "Overtime", "language": "JavaScript", "level": "Function", "summary": ""}, "commits_list": ["596cf52d", "d5437856"], "edges": [{"id": 61, "before": "select2.js#updateResults", "lineB": 1583, "after": "select2.js.prepareOpts#createSearchChoicePosition", "lineA": 1018, "ref": "EXTRACT_MOVE", "sha1": "596cf52d"}, {"id": 71, "before": "select2.js#updateResults", "lineB": 1321, "after": "select2.js#getMaximumSelectionSize", "lineA": 1162, "ref": "EXTRACT", "sha1": "d5437856"}]}