{"info": {"project": "quilljs/quill", "developers": 1, "edges": 5, "vertices": 6, "commits": 2, "id": 24, "agedays": 229, "refactorings": 3, "group": "Overtime", "language": "JavaScript", "level": "Function", "summary": ""}, "commits_list": ["aee9b867", "e1d76d9f"], "edges": [{"id": 74, "before": "core.quill.js.Quill#formatCursor", "lineB": 120, "after": "core.quill.js.Quill#format", "lineA": 120, "ref": "RENAME", "sha1": "aee9b867"}, {"id": 28, "before": "core.quill.js.Quill#setContents", "lineB": 244, "after": "core.quill.js.Quill#isEnabled", "lineA": 221, "ref": "EXTRACT", "sha1": "e1d76d9f"}, {"id": 29, "before": "core.quill.js.Quill#updateContents", "lineB": 279, "after": "core.quill.js.Quill#isEnabled", "lineA": 221, "ref": "EXTRACT", "sha1": "e1d76d9f"}, {"id": 30, "before": "core.quill.js#modify", "lineB": 373, "after": "core.quill.js.Quill#isEnabled", "lineA": 221, "ref": "EXTRACT_MOVE", "sha1": "e1d76d9f"}, {"id": 31, "before": "core.quill.js.Quill#format", "lineB": 128, "after": "core.quill.js.Quill#isEnabled", "lineA": 221, "ref": "EXTRACT", "sha1": "e1d76d9f"}]}