{"info": {"project": "PhilJay/MPAndroidChart", "developers": 1, "edges": 3, "vertices": 4, "commits": 3, "id": 296, "agedays": 166, "refactorings": 3, "group": "Overtime", "language": "Java", "level": "Method"}, "commits_list": ["e3f3dded", "ae7cbb4c", "61a476f0"], "edges": [{"id": 362, "before": "MPChartLib.src.com.github.mikephil.charting.charts.RadarChart#drawDataSet(int)", "lineB": null, "after": "MPChartLib.src.com.github.mikephil.charting.renderer.RadarChartRenderer#drawDataSet(Canvas,RadarDataSet)", "lineA": null, "ref": "MOVE", "sha1": "e3f3dded"}, {"id": 445, "before": "MPChartLib.src.com.github.mikephil.charting.charts.RadarChart#drawData()", "lineB": null, "after": "MPChartLib.src.com.github.mikephil.charting.charts.RadarChart#drawDataSet(int)", "lineA": null, "ref": "RENAME", "sha1": "ae7cbb4c"}, {"id": 537, "before": "MPChartLib.src.com.github.mikephil.charting.charts.RadarChart#drawData()", "lineB": null, "after": "MPChartLib.src.com.github.mikephil.charting.charts.RadarChart#getSliceAngle()", "lineA": null, "ref": "EXTRACT", "sha1": "61a476f0"}]}