{"info": {"project": "PhilJay/MPAndroidChart", "developers": 1, "edges": 1, "vertices": 2, "commits": 1, "id": 214, "agedays": 0, "refactorings": 1, "group": "Atomic", "language": "Java", "level": "Method"}, "commits_list": ["5a15715b"], "edges": [{"id": 235, "before": "MPChartLib.src.com.github.mikephil.charting.utils.ValueFormatter#getFormattedValue(float)", "lineB": null, "after": "MPChartLib.src.com.github.mikephil.charting.formatter.YAxisValueFormatter#getFormattedValue(float,YAxis)", "lineA": null, "ref": "MOVE", "sha1": "5a15715b"}]}