{"info": {"project": "PhilJay/MPAndroidChart", "developers": 1, "edges": 1, "vertices": 2, "commits": 1, "id": 436, "agedays": 0, "refactorings": 1, "group": "Atomic", "language": "Java", "level": "Method"}, "commits_list": ["1b5f8d4b"], "edges": [{"id": 638, "before": "MPChartLib.src.com.github.mikephil.charting.Chart#getMaxScale()", "lineB": null, "after": "MPChartLib.src.com.github.mikephil.charting.charts.BarLineChartBase#getMaxScaleX()", "lineA": null, "ref": "MOVE_RENAME", "sha1": "1b5f8d4b"}]}