{"info": {"project": "PhilJay/MPAndroidChart", "developers": 1, "edges": 1, "vertices": 2, "commits": 1, "id": 363, "agedays": 0, "refactorings": 1, "group": "Atomic", "language": "Java", "level": "Method", "summary": ""}, "commits_list": ["71a5a1ee"], "edges": [{"id": 520, "before": "MPChartLib.src.com.github.mikephil.charting.charts.BarLineChartBase#getClosestDataSetIndex(ArrayList,float)", "lineB": null, "after": "MPChartLib.src.com.github.mikephil.charting.utils.Utils#getClosestDataSetIndex(ArrayList,float)", "lineA": null, "ref": "MOVE", "sha1": "71a5a1ee"}]}