{"info": {"project": "PhilJay/MPAndroidChart", "developers": 1, "edges": 1, "vertices": 2, "commits": 1, "id": 431, "agedays": 0.0, "refactorings": 1, "group": "Atomic", "language": "Java", "level": "Method"}, "commits_list": ["13104b26"], "edges": [{"id": 628, "before": "MPChartLib.src.com.github.mikephil.charting.charts.BarLineChartBase#setYLegendTypeface(Typeface)", "lineB": null, "after": "MPChartLib.src.com.github.mikephil.charting.charts.BarLineChartBase#setYLabelTypeface(Typeface)", "lineA": null, "ref": "RENAME", "sha1": "13104b26"}]}