{"info": {"project": "PhilJay/MPAndroidChart", "developers": 1, "edges": 6, "vertices": 7, "commits": 1, "id": 294, "agedays": 0, "refactorings": 2, "group": "Atomic", "language": "Java", "level": "Method", "summary": ""}, "commits_list": ["e3f3dded"], "edges": [{"id": 364, "before": "MPChartLib.src.com.github.mikephil.charting.charts.RadarChart#drawWeb()", "lineB": null, "after": "MPChartLib.src.com.github.mikephil.charting.renderer.RadarChartRenderer#drawWeb(Canvas)", "lineA": null, "ref": "MOVE", "sha1": "e3f3dded"}, {"id": 366, "before": "MPChartLib.src.com.github.mikephil.charting.charts.RadarChart#drawWeb()", "lineB": null, "after": "MPChartLib.src.com.github.mikephil.charting.charts.RadarChart#getWebLineWidthInner()", "lineA": null, "ref": "EXTRACT", "sha1": "e3f3dded"}, {"id": 367, "before": "MPChartLib.src.com.github.mikephil.charting.charts.RadarChart#drawWeb()", "lineB": null, "after": "MPChartLib.src.com.github.mikephil.charting.charts.RadarChart#getWebLineWidth()", "lineA": null, "ref": "EXTRACT", "sha1": "e3f3dded"}, {"id": 371, "before": "MPChartLib.src.com.github.mikephil.charting.charts.RadarChart#drawWeb()", "lineB": null, "after": "MPChartLib.src.com.github.mikephil.charting.charts.RadarChart#getWebColor()", "lineA": null, "ref": "EXTRACT", "sha1": "e3f3dded"}, {"id": 358, "before": "MPChartLib.src.com.github.mikephil.charting.charts.RadarChart#drawWeb()", "lineB": null, "after": "MPChartLib.src.com.github.mikephil.charting.charts.RadarChart#getWebAlpha()", "lineA": null, "ref": "EXTRACT", "sha1": "e3f3dded"}, {"id": 360, "before": "MPChartLib.src.com.github.mikephil.charting.charts.RadarChart#drawWeb()", "lineB": null, "after": "MPChartLib.src.com.github.mikephil.charting.charts.RadarChart#getWebColorInner()", "lineA": null, "ref": "EXTRACT", "sha1": "e3f3dded"}]}