{"info": {"project": "facebook/fresco", "developers": 1, "edges": 1, "vertices": 2, "commits": 1, "id": 129, "agedays": 0.0, "refactorings": 1, "group": "Atomic", "language": "Java", "level": "Method"}, "commits_list": ["5313c66f"], "edges": [{"entity_before_full_name": "imagepipeline.src.main.com.facebook.imagepipeline.decoder.ImageDecoder#decodeGif(EncodedImage,ImageDecodeOptions)", "entity_after_full_name": "imagepipeline.src.main.com.facebook.imagepipeline.decoder.DefaultImageDecoder#decodeGif(EncodedImage,ImageDecodeOptions)", "refactoring_name": "PUSH_DOWN", "sha1": "5313c66f"}]}