{"info": {"project": "facebook/fresco", "developers": 1, "edges": 1, "vertices": 2, "commits": 1, "id": 94, "agedays": 0, "refactorings": 1, "group": "Atomic", "language": "Java", "level": "Method"}, "commits_list": ["555322f7"], "edges": [{"id": 107, "before": "drawee-backends.drawee-pipeline.src.main.com.facebook.drawee.backends.pipeline.PipelineDraweeControllerFactory#wrapAnimatedDrawableFactory(AnimatedDrawableFactory)", "lineB": null, "after": "animated-base.src.main.com.facebook.imagepipeline.animated.factory.AnimatedFactoryImpl#wrapAnimatedDrawableFactory(AnimatedDrawableFactory)", "lineA": null, "ref": "MOVE", "sha1": "555322f7"}]}