{"info": {"project": "airbnb/lottie-android", "developers": 1, "edges": 2, "vertices": 3, "commits": 1, "id": 122, "agedays": 0.0, "refactorings": 1, "group": "Atomic", "language": "Java", "level": "Method"}, "commits_list": ["07430f15"], "edges": [{"entity_before_full_name": "lottie.src.main.com.airbnb.lottie.AnimatableIntegerValue#valueFromObject(Object,float)", "entity_after_full_name": "lottie.src.main.com.airbnb.lottie.JsonUtils#valueFromObject(Object)", "refactoring_name": "EXTRACT_MOVE", "sha1": "07430f15"}, {"entity_before_full_name": "lottie.src.main.com.airbnb.lottie.AnimatableFloatValue#valueFromObject(Object,float)", "entity_after_full_name": "lottie.src.main.com.airbnb.lottie.JsonUtils#valueFromObject(Object)", "refactoring_name": "EXTRACT_MOVE", "sha1": "07430f15"}]}