{"info": {"project": "Leaflet/Leaflet", "developers": 1, "edges": 5, "vertices": 6, "commits": 3, "id": 96, "agedays": 1371.9936921296296, "refactorings": 2, "group": "Overtime", "language": "JavaScript", "level": "Function"}, "commits_list": ["08cf1ef0", "b0d6bcb0", "18a8a286"], "edges": [{"entity_before_full_name": "src.layer.ImageOverlay.js#_initInteraction", "entity_after_full_name": "src.layer.ImageOverlay.js#onAdd", "refactoring_name": "INLINE", "sha1": "08cf1ef0"}, {"entity_before_full_name": "src.layer.ImageOverlay.js#onAdd", "entity_after_full_name": "src.layer.ImageOverlay.js#_getPane", "refactoring_name": "EXTRACT", "sha1": "b0d6bcb0"}, {"entity_before_full_name": "src.layer.ImageOverlay.js#onAdd", "entity_after_full_name": "src.layer.ImageOverlay.js#_initImage", "refactoring_name": "EXTRACT", "sha1": "18a8a286"}, {"entity_before_full_name": "src.layer.ImageOverlay.js#bringToBack", "entity_after_full_name": "src.layer.ImageOverlay.js#_getPane", "refactoring_name": "EXTRACT", "sha1": "b0d6bcb0"}, {"entity_before_full_name": "src.layer.ImageOverlay.js#bringToFront", "entity_after_full_name": "src.layer.ImageOverlay.js#_getPane", "refactoring_name": "EXTRACT", "sha1": "b0d6bcb0"}]}