{"info": {"project": "bumptech/glide", "developers": 1, "edges": 1, "vertices": 2, "commits": 1, "id": 2, "agedays": 0, "refactorings": 1, "group": "Atomic", "language": "Java", "level": "Method"}, "commits_list": ["79dac0d1f"], "edges": [{"id": 4, "before": "library.src.main.com.bumptech.glide.load.resource.bitmap.Downsampler#calculateScaling(ImageType,InputStream,DecodeCallbacks,BitmapPool,DownsampleStrategy,int,int,int,int,int,BitmapFactory.Options)", "lineB": null, "after": "library.src.main.com.bumptech.glide.load.resource.bitmap.Downsampler#isRotationRequired(int)", "lineA": null, "ref": "EXTRACT", "sha1": "79dac0d1f"}]}