{"info": {"project": "refactoring-graph/refactoring-fowler-S22", "developers": 1, "edges": 2, "vertices": 3, "commits": 2, "id": 1, "agedays": 0, "refactorings": 1, "group": "Overtime", "language": "Java", "level": "Method", "summary": ""}, "commits_list": ["7bd72cc", "8a5ae58"], "edges": [{"id": 9, "before": "Rental#getFrequentRenterPoints()", "lineB": 18, "after": "Movie#getFrequentRenterPoints(int)", "lineA": 27, "ref": "EXTRACT_MOVE", "sha1": "7bd72cc"}, {"id": 4, "before": "Movie#getFrequentRenterPoints(int)", "lineB": 39, "after": "Price#getFrequentRenterPoints(int)", "lineA": 5, "ref": "EXTRACT_MOVE", "sha1": "8a5ae58"}]}