{"info": {"project": "vuejs/vue", "developers": 1, "edges": 2, "vertices": 2, "commits": 2, "id": 124, "agedays": 130.21363425925927, "refactorings": 1, "group": "Overtime", "language": "JavaScript", "level": "Function"}, "commits_list": ["cb1bb75b", "1d8f3a26"], "edges": [{"entity_before_full_name": "src.core.instance.init.js.initMixin#initInternalComponent", "entity_after_full_name": "src.core.instance.init.js#initInternalComponent", "refactoring_name": "INTERNAL_MOVE", "sha1": "cb1bb75b"}, {"entity_before_full_name": "src.core.instance.init.js#initInternalComponent", "entity_after_full_name": "src.core.instance.init.js.initMixin#initInternalComponent", "refactoring_name": "INTERNAL_MOVE", "sha1": "1d8f3a26"}]}