{"info": {"project": "nylas/nylas-mail", "developers": 1, "edges": 6, "vertices": 7, "commits": 2, "id": 68, "agedays": 143, "refactorings": 2, "group": "Overtime", "language": "JavaScript", "level": "Function"}, "commits_list": ["455b4563a", "304c34f91"], "edges": [{"id": 79, "before": "src.error-reporter.js#ErrorReporter", "lineB": 43, "after": "src.error-logger.js#ErrorLogger", "lineA": 42, "ref": "RENAME", "sha1": "455b4563a"}, {"id": 80, "before": "src.error-reporter.js#ErrorReporter", "lineB": 27, "after": "src.error-reporter.js#_hookProcessOutputs", "lineA": 99, "ref": "EXTRACT", "sha1": "304c34f91"}, {"id": 81, "before": "src.error-reporter.js#ErrorReporter", "lineB": 27, "after": "src.error-reporter.js#_setupNewLogFile", "lineA": 83, "ref": "EXTRACT", "sha1": "304c34f91"}, {"id": 82, "before": "src.error-reporter.js#ErrorReporter", "lineB": 27, "after": "src.error-reporter.js#_catchUncaughtErrors", "lineA": 126, "ref": "EXTRACT", "sha1": "304c34f91"}, {"id": 84, "before": "src.error-reporter.js#ErrorReporter", "lineB": 27, "after": "src.error-reporter.js#_cleanOldLogFiles", "lineA": 58, "ref": "EXTRACT", "sha1": "304c34f91"}, {"id": 85, "before": "src.error-reporter.js#ErrorReporter", "lineB": 27, "after": "src.error-reporter.js#_setupSentry", "lineA": 45, "ref": "EXTRACT", "sha1": "304c34f91"}]}